{
  "name": "TG-08-welcome-series",
  "nodes": [
    {
      "parameters": { "rule": { "interval": [{ "field": "cronExpression", "expression": "0 14 * * *" }] } },
      "id": "schedule",
      "name": "Daily 9am CT",
      "type": "n8n-nodes-base.scheduleTrigger",
      "typeVersion": 1.2,
      "position": [0, 300]
    },
    {
      "parameters": {
        "method": "GET",
        "url": "=={{$vars.TG_SUPABASE_URL}}/rest/v1/customers?welcome_series_started=eq.false&first_job_completed_at=not.is.null&select=id,first_name,last_name,email,phone,last_service,first_job_completed_at,city",
        "sendHeaders": true,
        "headerParameters": { "parameters": [{ "name": "apikey", "value": "={{$vars.TG_SUPABASE_ANON_KEY}}" }, { "name": "Authorization", "value": "=Bearer {{$vars.TG_SUPABASE_SERVICE_KEY}}" }] }
      },
      "id": "fetch-new-customers",
      "name": "Fetch New Customers",
      "type": "n8n-nodes-base.httpRequest",
      "typeVersion": 4.2,
      "position": [220, 300]
    },
    {
      "parameters": {
        "method": "GET",
        "url": "=={{$vars.TG_SUPABASE_URL}}/rest/v1/email_sends?workflow_name=eq.welcome_series&select=contact_email,email_type",
        "sendHeaders": true,
        "headerParameters": { "parameters": [{ "name": "apikey", "value": "={{$vars.TG_SUPABASE_ANON_KEY}}" }, { "name": "Authorization", "value": "=Bearer {{$vars.TG_SUPABASE_SERVICE_KEY}}" }] }
      },
      "id": "fetch-sent-history",
      "name": "Fetch Sent History",
      "type": "n8n-nodes-base.httpRequest",
      "typeVersion": 4.2,
      "position": [220, 500]
    },
    {
      "parameters": {
        "jsCode": "const customers = $('Fetch New Customers').all().map(i => i.json);\nconst sentHistory = $('Fetch Sent History').all().map(i => i.json);\n\nconst alreadySent = new Set();\nfor (const s of sentHistory) {\n  if (s.contact_email && s.email_type) {\n    alreadySent.add(s.contact_email + '|' + s.email_type);\n  }\n}\n\n// ── HTML email builder ──\nconst FONT = \"-apple-system,BlinkMacSystemFont,'Segoe UI',Roboto,Helvetica,Arial,sans-serif\";\nconst GREEN = '#2D5A27';\nconst GOLD = '#C5A55A';\n\nfunction checkItem(text) {\n  return '<tr><td style=\"padding:0 32px 16px;\"><table role=\"presentation\" cellspacing=\"0\" cellpadding=\"0\" border=\"0\" width=\"100%\"><tr><td width=\"44\" valign=\"top\" style=\"padding-right:12px;\"><table role=\"presentation\" cellspacing=\"0\" cellpadding=\"0\" border=\"0\"><tr><td align=\"center\" valign=\"middle\" width=\"36\" height=\"36\" style=\"background-color:#eaf5e8; border-radius:50%;\"><span style=\"font-size:18px; line-height:36px; color:' + GREEN + ';\">&#10003;</span></td></tr></table></td><td valign=\"middle\" style=\"font-family:' + FONT + '; font-size:15px; color:#1a1a1a; line-height:1.5;\">' + text + '</td></tr></table></td></tr>';\n}\n\nfunction reviewBlock(reviewText, reviewerName) {\n  return '<tr><td style=\"padding:0 32px 32px;\"><table role=\"presentation\" cellspacing=\"0\" cellpadding=\"0\" border=\"0\" width=\"100%\" style=\"background-color:#f9f9f9; border-radius:8px;\"><tr><td align=\"center\" style=\"padding:28px 28px 8px;\"><span style=\"font-size:24px; color:' + GOLD + '; letter-spacing:2px;\">&#9733;&#9733;&#9733;&#9733;&#9733;</span></td></tr><tr><td align=\"center\" style=\"padding:8px 28px;\"><p style=\"margin:0; font-family:Georgia,\\'Times New Roman\\',Times,serif; font-size:15px; color:#333333; line-height:1.7; font-style:italic;\">&ldquo;' + reviewText + '&rdquo;</p></td></tr><tr><td align=\"center\" style=\"padding:12px 28px 4px;\"><p style=\"margin:0; font-family:' + FONT + '; font-size:14px; color:#1a1a1a; font-weight:700; line-height:1.4;\">&mdash; ' + reviewerName + '</p></td></tr><tr><td align=\"center\" style=\"padding:0 28px 28px;\"><p style=\"margin:0; font-family:' + FONT + '; font-size:12px; color:#888888; line-height:1.4; text-transform:uppercase; letter-spacing:0.5px;\">Verified Google Review</p></td></tr></table></td></tr>';\n}\n\nfunction miniReviewBlock(reviews) {\n  let rows = '';\n  for (const r of reviews) {\n    rows += '<tr><td style=\"padding:8px 28px; border-bottom:1px solid #eeeeee;\"><p style=\"margin:0 0 4px; font-family:' + FONT + '; font-size:14px; color:#1a1a1a; font-weight:700;\"><span style=\"color:' + GOLD + ';\">&#9733;&#9733;&#9733;&#9733;&#9733;</span> ' + r.name + '</p><p style=\"margin:0; font-family:Georgia,\\'Times New Roman\\',Times,serif; font-size:14px; color:#555555; line-height:1.5; font-style:italic;\">&ldquo;' + r.text + '&rdquo;</p></td></tr>';\n  }\n  return '<tr><td style=\"padding:0 32px 32px;\"><table role=\"presentation\" cellspacing=\"0\" cellpadding=\"0\" border=\"0\" width=\"100%\" style=\"background-color:#f9f9f9; border-radius:8px;\"><tr><td align=\"center\" style=\"padding:24px 28px 8px;\"><p style=\"margin:0; font-family:' + FONT + '; font-size:13px; color:#555555; text-transform:uppercase; letter-spacing:1.5px; font-weight:700;\">What Your Neighbors Are Saying</p></td></tr>' + rows + '<tr><td align=\"center\" style=\"padding:12px 28px 24px;\"><p style=\"margin:0; font-family:' + FONT + '; font-size:12px; color:#888888; text-transform:uppercase; letter-spacing:0.5px;\">Verified Google Reviews</p></td></tr></table></td></tr>';\n}\n\nfunction ctaButton(text, url) {\n  return '<tr><td style=\"padding:0 32px 32px;\" align=\"center\"><table role=\"presentation\" cellspacing=\"0\" cellpadding=\"0\" border=\"0\" style=\"width:100%;\"><tr><td align=\"center\" style=\"border-radius:6px; background-color:' + GREEN + ';\"><a href=\"' + url + '\" target=\"_blank\" style=\"display:block; padding:16px 32px; font-family:' + FONT + '; font-size:16px; font-weight:700; color:#ffffff; text-decoration:none; border-radius:6px; background-color:' + GREEN + '; text-align:center;\">' + text + '</a></td></tr></table></td></tr>';\n}\n\nfunction buildHtml(opts) {\n  // opts: { firstName, previewText, bannerTitle, bannerSub, bodyHtml, reviewHtml, ctaText, ctaUrl, showWelcomeBanner }\n  const headerBar = '<tr><td style=\"background-color:' + GREEN + ';\"><table role=\"presentation\" cellspacing=\"0\" cellpadding=\"0\" border=\"0\" width=\"100%\"><tr><td style=\"padding:16px 24px;\"><table role=\"presentation\" cellspacing=\"0\" cellpadding=\"0\" border=\"0\" width=\"100%\"><tr><td align=\"left\" valign=\"middle\" style=\"font-family:' + FONT + '; font-size:18px; font-weight:700; color:#ffffff; line-height:1.3;\">TotalGuard Yard Care</td><td align=\"right\" valign=\"middle\" style=\"font-family:' + FONT + '; font-size:14px; color:#ffffff; line-height:1.3;\"><a href=\"tel:+16085356057\" style=\"color:#ffffff; text-decoration:none; font-weight:600;\">(608) 535-6057</a></td></tr></table></td></tr><tr><td align=\"center\" style=\"padding:0 24px 14px; font-family:' + FONT + '; font-size:13px; color:' + GOLD + '; letter-spacing:1.5px; text-transform:uppercase; font-weight:600;\">Madison\\'s Most Trusted Yard Care</td></tr></table></td></tr>';\n\n  let banner = '';\n  if (opts.showWelcomeBanner) {\n    banner = '<tr><td style=\"background: linear-gradient(135deg, #2D5A27 0%, #3d7a34 50%, #2D5A27 100%);\"><table role=\"presentation\" cellspacing=\"0\" cellpadding=\"0\" border=\"0\" width=\"100%\"><tr><td align=\"center\" style=\"padding:48px 32px 16px;\"><h1 style=\"margin:0; font-family:' + FONT + '; font-size:32px; font-weight:800; color:#ffffff; line-height:1.2;\">' + opts.bannerTitle + '</h1></td></tr><tr><td align=\"center\" style=\"padding:8px 40px 48px;\"><p style=\"margin:0; font-family:' + FONT + '; font-size:16px; color:' + GOLD + '; line-height:1.5; font-weight:500;\">' + opts.bannerSub + '</p></td></tr></table></td></tr>';\n  } else if (opts.bannerTitle) {\n    banner = '<tr><td style=\"background-color:' + GREEN + ';\"><table role=\"presentation\" cellspacing=\"0\" cellpadding=\"0\" border=\"0\" width=\"100%\"><tr><td align=\"center\" style=\"padding:32px;\"><h1 style=\"margin:0; font-family:' + FONT + '; font-size:26px; font-weight:800; color:#ffffff; line-height:1.2;\">' + opts.bannerTitle + '</h1></td></tr></table></td></tr>';\n  }\n\n  const trustBar = '<tr><td style=\"padding:0 32px 24px;\"><table role=\"presentation\" cellspacing=\"0\" cellpadding=\"0\" border=\"0\" width=\"100%\" style=\"background-color:' + GREEN + '; border-radius:6px;\"><tr><td align=\"center\" style=\"padding:14px 16px; font-family:' + FONT + '; font-size:12px; color:#ffffff; line-height:2; letter-spacing:0.3px;\">&#10003; Licensed &amp; Insured&nbsp;&nbsp;&bull;&nbsp;&nbsp;&#10003; 4.9&#9733; Rating&nbsp;&nbsp;&bull;&nbsp;&nbsp;&#10003; 500+ Properties&nbsp;&nbsp;&bull;&nbsp;&nbsp;&#10003; 100% Satisfaction Guarantee</td></tr></table></td></tr>';\n\n  const footer = '<tr><td style=\"background-color:#1a1a1a; border-radius:0 0 8px 8px;\"><table role=\"presentation\" cellspacing=\"0\" cellpadding=\"0\" border=\"0\" width=\"100%\"><tr><td align=\"center\" style=\"padding:32px 32px 8px;\"><p style=\"margin:0; font-family:' + FONT + '; font-size:18px; font-weight:700; color:#ffffff; line-height:1.3;\">TotalGuard Yard Care</p></td></tr><tr><td align=\"center\" style=\"padding:4px 32px;\"><p style=\"margin:0; font-family:' + FONT + '; font-size:13px; color:#999999; line-height:1.6;\">Madison, WI&nbsp;&nbsp;|&nbsp;&nbsp;<a href=\"tel:+16085356057\" style=\"color:' + GOLD + '; text-decoration:none;\">(608) 535-6057</a>&nbsp;&nbsp;|&nbsp;&nbsp;<a href=\"mailto:info@tgyardcare.com\" style=\"color:' + GOLD + '; text-decoration:none;\">info@tgyardcare.com</a></p></td></tr><tr><td align=\"center\" style=\"padding:20px 32px 8px;\"><table role=\"presentation\" cellspacing=\"0\" cellpadding=\"0\" border=\"0\"><tr><td style=\"padding:0 8px;\"><a href=\"https://www.facebook.com/totalguardyard/\" target=\"_blank\" style=\"font-family:' + FONT + '; font-size:13px; color:' + GOLD + '; text-decoration:none;\">Facebook</a></td><td style=\"padding:0 8px;\"><a href=\"https://www.instagram.com/totalguardyardcare\" target=\"_blank\" style=\"font-family:' + FONT + '; font-size:13px; color:' + GOLD + '; text-decoration:none;\">Instagram</a></td><td style=\"padding:0 8px;\"><a href=\"https://g.page/r/CRW5Dsg2JgwBEBM\" target=\"_blank\" style=\"font-family:' + FONT + '; font-size:13px; color:' + GOLD + '; text-decoration:none;\">Google</a></td></tr></table></td></tr><tr><td align=\"center\" style=\"padding:12px 32px;\"><p style=\"margin:0; font-family:' + FONT + '; font-size:11px; color:#666666; line-height:1.6;\">Serving Madison, Middleton, Fitchburg, Sun Prairie, Verona, Waunakee &amp; surrounding areas</p></td></tr><tr><td align=\"center\" style=\"padding:8px 32px 32px;\"><p style=\"margin:0; font-family:' + FONT + '; font-size:11px; color:#666666; line-height:1.6;\">You\\'re receiving this because you signed up with TotalGuard Yard Care.<br><a href=\"https://tgyardcare.com/unsubscribe\" style=\"color:#999999; text-decoration:underline;\">Unsubscribe</a>&nbsp;&nbsp;|&nbsp;&nbsp;<a href=\"https://tgyardcare.com/email-preferences\" style=\"color:#999999; text-decoration:underline;\">Email Preferences</a></p></td></tr></table></td></tr>';\n\n  const style = '<style type=\"text/css\">body,table,td,a{-webkit-text-size-adjust:100%;-ms-text-size-adjust:100%}table,td{mso-table-lspace:0pt;mso-table-rspace:0pt}img{-ms-interpolation-mode:bicubic;border:0;height:auto;line-height:100%;outline:none;text-decoration:none}body{margin:0;padding:0;width:100%!important;height:100%!important;background-color:#f4f4f4}@media only screen and (max-width:620px){.email-container{width:100%!important;max-width:100%!important}}</style>';\n\n  return '<!DOCTYPE html><html xmlns=\"http://www.w3.org/1999/xhtml\" lang=\"en\"><head><meta charset=\"utf-8\"><meta name=\"viewport\" content=\"width=device-width,initial-scale=1.0\">' + style + '</head><body style=\"margin:0;padding:0;background-color:#f4f4f4;\"><div style=\"display:none;font-size:1px;color:#f4f4f4;line-height:1px;max-height:0;max-width:0;opacity:0;overflow:hidden;\">' + (opts.previewText || '') + '</div><table role=\"presentation\" cellspacing=\"0\" cellpadding=\"0\" border=\"0\" width=\"100%\" style=\"background-color:#f4f4f4;\"><tr><td align=\"center\" valign=\"top\" style=\"padding:20px 0;\"><table role=\"presentation\" cellspacing=\"0\" cellpadding=\"0\" border=\"0\" width=\"600\" class=\"email-container\" style=\"margin:0 auto;max-width:600px;background-color:#ffffff;border-radius:8px;overflow:hidden;box-shadow:0 2px 8px rgba(0,0,0,0.06);\">' + headerBar + banner + opts.bodyHtml + (opts.reviewHtml || '') + ctaButton(opts.ctaText, opts.ctaUrl) + trustBar + footer + '</table></td></tr></table></body></html>';\n}\n\nfunction divider() {\n  return '<tr><td style=\"padding:0 32px;\"><table role=\"presentation\" cellspacing=\"0\" cellpadding=\"0\" border=\"0\" width=\"100%\"><tr><td style=\"border-top:1px solid #e8e8e8; font-size:1px; line-height:1px;\">&nbsp;</td></tr></table></td></tr>';\n}\n\nfunction paragraph(text) {\n  return '<tr><td style=\"padding:8px 32px;\"><p style=\"margin:0; font-family:' + FONT + '; font-size:15px; color:#333333; line-height:1.7;\">' + text + '</p></td></tr>';\n}\n\nfunction greeting(firstName) {\n  return '<tr><td style=\"padding:32px 32px 0;\"><p style=\"margin:0; font-family:' + FONT + '; font-size:18px; color:' + GREEN + '; font-weight:700; line-height:1.4;\">Hi ' + firstName + ',</p></td></tr>';\n}\n\nfunction signoff() {\n  return '<tr><td style=\"padding:16px 32px 32px;\"><p style=\"margin:0; font-family:' + FONT + '; font-size:15px; color:' + GREEN + '; font-weight:600; line-height:1.4;\">&mdash; Vance &amp; The TotalGuard Team</p></td></tr>';\n}\n\nfunction sectionTitle(text) {\n  return '<tr><td style=\"padding:32px 32px 8px;\"><h2 style=\"margin:0; font-family:' + FONT + '; font-size:22px; font-weight:700; color:#1a1a1a; line-height:1.3; text-align:center;\">' + text + '</h2></td></tr>';\n}\n\n// ── End HTML builder ──\n\nconst results = [];\nconst month = new Date().getMonth() + 1;\nconst seasonal = month >= 3 && month <= 5 ? 'spring cleanup and aeration' : month >= 6 && month <= 8 ? 'summer lawn care and fertilization' : month >= 9 && month <= 11 ? 'fall cleanup and gutter cleaning' : 'snow removal and winter prep';\nconst seasonalShort = month >= 3 && month <= 5 ? 'Spring Cleanup' : month >= 6 && month <= 8 ? 'Summer Care' : month >= 9 && month <= 11 ? 'Fall Cleanup' : 'Winter Prep';\n\nfor (const c of customers) {\n  if (!c.email) continue;\n  const daysSince = Math.floor((Date.now() - new Date(c.first_job_completed_at)) / (1000*60*60*24));\n  let emailNum = null, subject = '', body = '', htmlBody = '';\n\n  if (daysSince <= 1) {\n    emailNum = 1;\n    subject = 'Welcome to TotalGuard, ' + c.first_name + '!';\n    body = 'Hi ' + c.first_name + ',\\n\\nWelcome to TotalGuard Yard Care! We\\'re thrilled to have you as a customer.\\n\\nHere\\'s what happens next:\\n\\n✓ Your dedicated crew assigned within 24 hours\\n✓ Same team every visit — they learn your yard\\n✓ Service confirmation text before each visit\\n✓ Before & after photos after every job\\n\\nQuestions? Call us at (608) 535-6057 or reply to this email.\\n\\n- Vance & The TotalGuard Team';\n\n    const bodyHtml = greeting(c.first_name)\n      + paragraph('Welcome to TotalGuard Yard Care! We\\'re thrilled to have you as a customer. You just made the best decision for your yard.')\n      + paragraph('We don\\'t just cut grass &mdash; we build relationships. Here\\'s what you can expect as a TotalGuard customer:')\n      + divider()\n      + sectionTitle('Here\\'s What Happens Next')\n      + checkItem('<strong style=\"color:' + GREEN + ';\">Your dedicated crew assigned within 24 hours</strong>')\n      + checkItem('<strong style=\"color:' + GREEN + ';\">Same team every visit</strong> &mdash; they learn your yard')\n      + checkItem('<strong style=\"color:' + GREEN + ';\">Service confirmation text</strong> before each visit')\n      + checkItem('<strong style=\"color:' + GREEN + ';\">Before &amp; after photos</strong> after every job')\n      + divider();\n\n    const reviewHtml = reviewBlock('TotalGuard Lawn Service has been nothing short of outstanding! From the very first interaction, their proactive communication and reliability stood out.', 'Susan McBryde');\n\n    htmlBody = buildHtml({\n      firstName: c.first_name,\n      previewText: 'Your dedicated crew is being assigned now. Here\\'s what happens next...',\n      bannerTitle: 'Welcome to the TotalGuard Family!',\n      bannerSub: 'You just made the best decision for your yard.',\n      showWelcomeBanner: true,\n      bodyHtml: bodyHtml,\n      reviewHtml: reviewHtml,\n      ctaText: 'Save Our Number: (608) 535-6057',\n      ctaUrl: 'tel:+16085356057'\n    });\n  }\n  else if (daysSince === 7) {\n    emailNum = 2;\n    subject = 'The #1 mistake ' + (c.city || 'Madison') + ' homeowners make with their lawn';\n    body = 'Hi ' + c.first_name + ',\\n\\nA week in! Here are 3 pro tips to keep your yard looking great between visits:\\n\\n1. Water deeply 2-3x per week (early morning is best)\\n2. Never cut more than 1/3 of grass height at once\\n3. Keep mower blades sharp — dull blades tear grass and invite disease\\n\\nWant to take your lawn to the next level? Our fertilization program keeps your grass thick, green, and weed-free all season. Most customers see results within 2 weeks.\\n\\n- Vance & The TotalGuard Team';\n\n    const bodyHtml = greeting(c.first_name)\n      + paragraph('A week in! Your yard is already looking better. But here\\'s a secret most homeowners don\\'t know...')\n      + sectionTitle('3 Pro Tips for a Healthier Lawn')\n      + checkItem('<strong style=\"color:' + GREEN + ';\">Water deeply 2-3x per week</strong> &mdash; early morning is best. Light daily watering creates shallow roots.')\n      + checkItem('<strong style=\"color:' + GREEN + ';\">Never cut more than 1/3 of grass height</strong> &mdash; cutting too short stresses your lawn and invites weeds.')\n      + checkItem('<strong style=\"color:' + GREEN + ';\">Keep mower blades sharp</strong> &mdash; dull blades tear grass and invite disease. We sharpen ours every week.')\n      + divider()\n      + paragraph('Want to take your lawn to the next level? Our <strong>fertilization program</strong> keeps your grass thick, green, and weed-free all season. Most customers see visible results within 2 weeks.')\n      + signoff()\n      + divider();\n\n    const reviewHtml = reviewBlock('I recently purchased seasonal a round of herbicide treatment and I am beyond grateful for TotalGuard.', 'Nick Bauman');\n\n    htmlBody = buildHtml({\n      firstName: c.first_name,\n      previewText: 'The #1 mistake that kills Madison lawns (and 2 more pro tips)...',\n      bannerTitle: 'Pro Lawn Care Tips',\n      bannerSub: '',\n      showWelcomeBanner: false,\n      bodyHtml: bodyHtml,\n      reviewHtml: reviewHtml,\n      ctaText: 'Add Fertilization to My Plan',\n      ctaUrl: 'https://tgyardcare.com/services/fertilization?utm_source=email&utm_medium=welcome&utm_campaign=welcome_series_2'\n    });\n  }\n  else if (daysSince === 14) {\n    emailNum = 3;\n    subject = 'Quick favor, ' + c.first_name + '? (takes 30 seconds)';\n    body = 'Hi ' + c.first_name + ',\\n\\nWe hope you\\'re loving your yard! If we\\'ve exceeded your expectations, a quick Google review means the world to us.\\n\\nhttps://g.page/r/CRW5Dsg2JgwBEBM/review\\n\\nIt only takes 30 seconds and helps us serve more Madison neighbors like you.\\n\\nNot 100% satisfied? Reply to this email and tell us how we can make it right. We\\'ll fix it.\\n\\n- Vance & The TotalGuard Team';\n\n    const bodyHtml = greeting(c.first_name)\n      + paragraph('We hope you\\'re loving your yard! It\\'s been two weeks and we wanted to check in.')\n      + paragraph('If we\\'ve exceeded your expectations, a quick Google review means the <strong>world</strong> to us. It takes just 30 seconds and helps us serve more ' + (c.city || 'Madison') + ' neighbors like you.')\n      + divider();\n\n    const reviewHtml = miniReviewBlock([\n      { name: 'Maxi Schultz', text: 'Professional, reliable, and my yard has never looked better.' },\n      { name: 'Mason', text: 'Great communication and always on time. Highly recommend!' },\n      { name: 'Ian Fleck', text: 'They go above and beyond every single visit. Worth every penny.' }\n    ]) + '<tr><td style=\"padding:0 32px 16px;\"><table role=\"presentation\" cellspacing=\"0\" cellpadding=\"0\" border=\"0\" width=\"100%\" style=\"background-color:#faf9f6; border-radius:8px; border-left:4px solid ' + GOLD + ';\"><tr><td style=\"padding:20px 24px;\"><p style=\"margin:0; font-family:' + FONT + '; font-size:14px; color:#555555; line-height:1.6;\"><strong style=\"color:#1a1a1a;\">Not 100% satisfied?</strong> Reply to this email and tell us how we can make it right. We\\'ll fix it &mdash; guaranteed.</p></td></tr></table></td></tr>';\n\n    htmlBody = buildHtml({\n      firstName: c.first_name,\n      previewText: 'Quick favor? It takes just 30 seconds...',\n      bannerTitle: '',\n      bannerSub: '',\n      showWelcomeBanner: false,\n      bodyHtml: bodyHtml,\n      reviewHtml: reviewHtml,\n      ctaText: '\\u2605\\u2605\\u2605\\u2605\\u2605 Leave a Quick Review',\n      ctaUrl: 'https://g.page/r/CRW5Dsg2JgwBEBM/review'\n    });\n  }\n  else if (daysSince === 21) {\n    emailNum = 4;\n    subject = 'You\\'ve earned $25, ' + c.first_name + ' \\u2014 here\\'s how to claim it';\n    body = 'Hi ' + c.first_name + ',\\n\\nLove your yard? Share the love!\\n\\nHere\\'s the deal:\\n- You get $25 off your next service\\n- Your neighbor gets $25 off their first service\\n- No limit — refer as many neighbors as you want\\n\\nJust have them mention your name when they book at tgyardcare.com or call (608) 535-6057.\\n\\n- Vance & The TotalGuard Team';\n\n    const bodyHtml = greeting(c.first_name)\n      + paragraph('Love your yard? <strong>Share the love!</strong> As a thank-you for being a TotalGuard customer, we\\'re giving you $25 to share with a neighbor.')\n      + sectionTitle('Here\\'s the Deal')\n      + checkItem('<strong style=\"color:' + GREEN + ';\">You get $25 off</strong> your next service')\n      + checkItem('<strong style=\"color:' + GREEN + ';\">Your neighbor gets $25 off</strong> their first service')\n      + checkItem('<strong style=\"color:' + GREEN + ';\">No limit</strong> &mdash; refer as many neighbors as you want')\n      + divider()\n      + paragraph('Just have them mention your name when they book. It\\'s that easy.')\n      + signoff()\n      + divider();\n\n    const reviewHtml = reviewBlock('They handled a full mulch job plus weeding\\u2014looked so good I had to walk my neighbor through it. She hired them the next day.', 'Anderson See');\n\n    htmlBody = buildHtml({\n      firstName: c.first_name,\n      previewText: 'You\\'ve earned $25 — here\\'s how to claim it...',\n      bannerTitle: 'You\\'ve Earned $25!',\n      bannerSub: '',\n      showWelcomeBanner: false,\n      bodyHtml: bodyHtml,\n      reviewHtml: reviewHtml,\n      ctaText: 'Share With a Neighbor',\n      ctaUrl: 'https://tgyardcare.com/referral?utm_source=email&utm_medium=welcome&utm_campaign=welcome_series_4'\n    });\n  }\n  else if (daysSince === 30) {\n    emailNum = 5;\n    subject = c.first_name + ', your yard is ready for the next level';\n    body = 'Hi ' + c.first_name + ',\\n\\nNow that you\\'re settled in, have you considered adding ' + seasonal + ' to your plan?\\n\\nAs an existing customer, you save 10% when you add a new service. Book online at tgyardcare.com or call (608) 535-6057.\\n\\n- Vance & The TotalGuard Team';\n\n    const bodyHtml = greeting(c.first_name)\n      + paragraph('It\\'s been a month and your yard is looking great! But there\\'s always room to take it to the <strong>next level</strong>.')\n      + paragraph('This is the perfect time to add <strong>' + seasonal + '</strong> to your plan. As an existing customer, you save <strong>10%</strong> when you add any new service.')\n      + divider()\n      + sectionTitle('Why Add ' + seasonalShort + '?')\n      + checkItem('<strong style=\"color:' + GREEN + ';\">Protect your investment</strong> &mdash; seasonal care prevents costly damage')\n      + checkItem('<strong style=\"color:' + GREEN + ';\">Same trusted crew</strong> &mdash; no new strangers on your property')\n      + checkItem('<strong style=\"color:' + GREEN + ';\">Save 10%</strong> as an existing customer &mdash; exclusive rate')\n      + divider()\n      + signoff();\n\n    const reviewHtml = reviewBlock('Was very happy with my services and have added on more services they offer.', 'Kim Esser');\n\n    htmlBody = buildHtml({\n      firstName: c.first_name,\n      previewText: 'Your yard is ready for the next level. Save 10% on ' + seasonal + '.',\n      bannerTitle: 'Ready for the Next Level?',\n      bannerSub: '',\n      showWelcomeBanner: false,\n      bodyHtml: bodyHtml,\n      reviewHtml: reviewHtml,\n      ctaText: 'Add ' + seasonalShort + ' \\u2014 Save 10%',\n      ctaUrl: 'https://tgyardcare.com/services?utm_source=email&utm_medium=welcome&utm_campaign=welcome_series_5'\n    });\n  }\n\n  if (!emailNum) continue;\n\n  const emailType = 'welcome_series_' + emailNum;\n  if (alreadySent.has(c.email + '|' + emailType)) continue;\n\n  results.push({ json: { ...c, emailNum, subject, body, htmlBody, daysSince, emailType } });\n}\nreturn results;"
      },
      "id": "determine-email",
      "name": "Determine Email to Send",
      "type": "n8n-nodes-base.code",
      "typeVersion": 2,
      "position": [440, 400]
    },
    {
      "parameters": {
        "method": "POST",
        "url": "https://api.brevo.com/v3/smtp/email",
        "sendHeaders": true,
        "headerParameters": { "parameters": [{ "name": "api-key", "value": "={{$vars.TG_BREVO_API_KEY}}" }, { "name": "Content-Type", "value": "application/json" }] },
        "sendBody": true,
        "specifyBody": "json",
        "jsonBody": "={ \"sender\": { \"name\": \"TotalGuard Yard Care\", \"email\": \"totalguardllc@gmail.com\" }, \"to\": [{ \"email\": \"{{ $json.email }}\", \"name\": \"{{ $json.first_name }} {{ $json.last_name }}\" }], \"subject\": \"{{ $json.subject }}\", \"htmlContent\": \"{{ $json.htmlBody }}\", \"textContent\": \"{{ $json.body }}\" }"
      },
      "id": "send-email",
      "name": "Send via Brevo",
      "type": "n8n-nodes-base.httpRequest",
      "typeVersion": 4.2,
      "position": [660, 400],
      "continueOnFail": true
    },
    {
      "parameters": {
        "method": "POST",
        "url": "=={{$vars.TG_SUPABASE_URL}}/rest/v1/email_sends",
        "sendHeaders": true,
        "headerParameters": { "parameters": [{ "name": "apikey", "value": "={{$vars.TG_SUPABASE_ANON_KEY}}" }, { "name": "Authorization", "value": "=Bearer {{$vars.TG_SUPABASE_SERVICE_KEY}}" }, { "name": "Content-Type", "value": "application/json" }] },
        "sendBody": true,
        "specifyBody": "json",
        "jsonBody": "={\n  \"contact_email\": \"{{ $json.email }}\",\n  \"workflow_name\": \"welcome_series\",\n  \"email_type\": \"{{ $json.emailType }}\",\n  \"sequence_step\": {{ $json.emailNum }}\n}"
      },
      "id": "log-send",
      "name": "Log to email_sends",
      "type": "n8n-nodes-base.httpRequest",
      "typeVersion": 4.2,
      "position": [880, 400]
    },
    {
      "parameters": {
        "method": "POST",
        "url": "=={{$vars.TG_SUPABASE_URL}}/rest/v1/sequence_enrollments?on_conflict=contact_email,sequence_name",
        "sendHeaders": true,
        "headerParameters": { "parameters": [{ "name": "apikey", "value": "={{$vars.TG_SUPABASE_ANON_KEY}}" }, { "name": "Authorization", "value": "=Bearer {{$vars.TG_SUPABASE_SERVICE_KEY}}" }, { "name": "Content-Type", "value": "application/json" }, { "name": "Prefer", "value": "resolution=merge-duplicates" }] },
        "sendBody": true,
        "specifyBody": "json",
        "jsonBody": "={\n  \"contact_email\": \"{{ $json.email }}\",\n  \"sequence_name\": \"welcome_series\",\n  \"current_step\": {{ $json.emailNum }},\n  \"status\": {{ $json.emailNum >= 5 ? '\"completed\"' : '\"active\"' }}\n}"
      },
      "id": "upsert-enrollment",
      "name": "Upsert Enrollment",
      "type": "n8n-nodes-base.httpRequest",
      "typeVersion": 4.2,
      "position": [1100, 400],
      "continueOnFail": true
    }
  ],
  "connections": {
    "Daily 9am CT": { "main": [[{ "node": "Fetch New Customers", "type": "main", "index": 0 }, { "node": "Fetch Sent History", "type": "main", "index": 0 }]] },
    "Fetch New Customers": { "main": [[{ "node": "Determine Email to Send", "type": "main", "index": 0 }]] },
    "Fetch Sent History": { "main": [[{ "node": "Determine Email to Send", "type": "main", "index": 0 }]] },
    "Determine Email to Send": { "main": [[{ "node": "Send via Brevo", "type": "main", "index": 0 }]] },
    "Send via Brevo": { "main": [[{ "node": "Log to email_sends", "type": "main", "index": 0 }]] },
    "Log to email_sends": { "main": [[{ "node": "Upsert Enrollment", "type": "main", "index": 0 }]] }
  },
  "settings": { "availableInMCP": true }
}